./.gitignore
./Dockerfile
./PKG-INFO
./README.md
./README_zh.md
./cursor_config.json
./docker-compose.yml
./pyproject.toml
./requirements.txt
./smithery.yaml
./uml_mcp_server.py
iflow_mcp_uml_mcp_server-0.1.0.dist-info/METADATA
iflow_mcp_uml_mcp_server-0.1.0.dist-info/WHEEL
iflow_mcp_uml_mcp_server-0.1.0.dist-info/entry_points.txt
iflow_mcp_uml_mcp_server-0.1.0.dist-info/RECORD
