Metadata-Version: 2.4
Name: iflow-mcp_uml-mcp-server
Version: 0.1.0
Summary: UML diagram generation tool based on MCP (Model Context Protocol)
Requires-Python: >=3.10
Requires-Dist: mcp>=1.2.0
Requires-Dist: python-dateutil>=2.8.2
Requires-Dist: requests>=2.28.0
